README.md
setup.cfg
setup.py
mls/__init__.py
mls/client/__init__.py
mls/client/client.py
mls/client/utils.py
mls/server/__init__.py
mls/server/base.py
mls/server/preparator.py
mls/server/server.py
mls/server/state_machine.py
mls/server/utils.py
myLittleServer.egg-info/PKG-INFO
myLittleServer.egg-info/SOURCES.txt
myLittleServer.egg-info/dependency_links.txt
myLittleServer.egg-info/requires.txt
myLittleServer.egg-info/top_level.txt