Metadata-Version: 1.1
Name: myLittleServer
Version: 1.2.3
Summary: mls is a wrapper around ml code.
Home-page: https://github.com/connectome-ai/mls
Author: connectome.ai
Author-email: UNKNOWN
License: UNKNOWN
Download-URL: https://github.com/connectome-ai/mls/archive/1.2.3.tar.gz
Platform: UNKNOWN
